{
    "name": "scene",
    "objects": [
        {
            "type": "MESH",
            "name": "立方体.001",
            "transform": {
                "translation": [
                    0.0,
                    0.0,
                    0.0
                ],
                "rotation": [
                    0.0,
                    -0.0,
                    0.0
                ],
                "scaling": [
                    1.0,
                    1.0,
                    1.0
                ]
            },
            "file_name": "obj0"
        },
        {
            "type": "MESH",
            "name": "円柱",
            "transform": {
                "translation": [
                    23.307506561279297,
                    0.6252763271331787,
                    8.981870651245117
                ],
                "rotation": [
                    86.93208312988281,
                    -18.035247802734375,
                    -74.24898529052734
                ],
                "scaling": [
                    1.0,
                    0.9999999403953552,
                    1.0
                ]
            },
            "file_name": "SelectPoint"
        }
    ]
}